magic_numbers.py
magic_numbers-1.0.3.dist-info/LICENSE
magic_numbers-1.0.3.dist-info/METADATA
magic_numbers-1.0.3.dist-info/WHEEL
magic_numbers-1.0.3.dist-info/top_level.txt
magic_numbers-1.0.3.dist-info/RECORD
