Metadata-Version: 2.1
Name: magic-numbers
Version: 1.0.3
Summary: magically import magic number constants
Requires-Python: >=3.10
License-File: LICENSE
